MANIFEST.in
README.md
setup.py
radarfacerecog/__init__.py
radarfacerecog/politicos.csv
radarfacerecog/scrapper.py
radarfacerecog.egg-info/PKG-INFO
radarfacerecog.egg-info/SOURCES.txt
radarfacerecog.egg-info/dependency_links.txt
radarfacerecog.egg-info/requires.txt
radarfacerecog.egg-info/top_level.txt
radarfacerecog/data/AJ Albuquerque.jpg
radarfacerecog/data/Abílio Santana.jpg
radarfacerecog/data/Abou Anni.jpg
radarfacerecog/data/Acácio Favacho.jpg
radarfacerecog/data/Acir Gurgacz.jpg
radarfacerecog/data/Adolfo Viana.jpg
radarfacerecog/data/Adriana Ventura.jpg
radarfacerecog/data/Adriano do Baldy.jpg
radarfacerecog/data/Aécio Neves.jpg
radarfacerecog/data/Afonso Florence.jpg
radarfacerecog/data/Afonso Hamm.jpg
radarfacerecog/data/Afonso Motta.jpg
radarfacerecog/data/Aguinaldo Ribeiro.jpg
radarfacerecog/data/Airton Faleiro.jpg
radarfacerecog/data/Alan Rick.jpg
radarfacerecog/data/Alceu Moreira.jpg
radarfacerecog/data/Alcides Rodrigues.jpg
radarfacerecog/data/Alencar Santana Braga.jpg
radarfacerecog/data/Alessandro Molon.jpg
radarfacerecog/data/Alex Manente.jpg
radarfacerecog/data/Alex Santana.jpg
radarfacerecog/data/Alexandre Frota.jpg
radarfacerecog/data/Alexandre Leite.jpg
radarfacerecog/data/Alexandre Padilha.jpg
radarfacerecog/data/Alexandre Serfiotis.jpg
radarfacerecog/data/Alexis Fonteyne.jpg
radarfacerecog/data/Alê Silva.jpg
radarfacerecog/data/Alice Portugal.jpg
radarfacerecog/data/Aliel Machado.jpg
radarfacerecog/data/Aline Gurgel.jpg
radarfacerecog/data/Aline Sleutjes.jpg
radarfacerecog/data/Altineu Côrtes.jpg
radarfacerecog/data/Aluisio Mendes.jpg
radarfacerecog/data/Alvaro Dias.jpg
radarfacerecog/data/Amaro Neto.jpg
radarfacerecog/data/André Abdon.jpg
radarfacerecog/data/André Ferreira.jpg
radarfacerecog/data/André Figueiredo.jpg
radarfacerecog/data/André Fufuca.jpg
radarfacerecog/data/André Janones.jpg
radarfacerecog/data/André de Paula.jpg
radarfacerecog/data/Angela Amin.jpg
radarfacerecog/data/Aníbal Gomes.jpg
radarfacerecog/data/Antonio Anastasia.jpg
radarfacerecog/data/Antonio Brito.jpg
radarfacerecog/data/Arlindo Chinaglia.jpg
radarfacerecog/data/Arnaldo Jardim.jpg
radarfacerecog/data/Arolde de Oliveira.jpg
